Metadata-Version: 2.1
Name: signess
Version: 0.0.1.2
Summary: Signess
Home-page: https://github.com/ElishaFlacon/signess
Author: Elisha Flacon
License: BSD 3-Clause
Download-URL: https://github.com/ElishaFlacon/signess/archive/main.zip
Platform: UNKNOWN
Classifier: License :: OSI Approved :: BSD License
Classifier: Intended Audience :: Developers
Classifier: Programming Language :: Python :: 3.8
Classifier: Programming Language :: Python :: 3.9
Classifier: Programming Language :: Python :: 3.10
Classifier: Programming Language :: Python :: 3.11
Requires-Python: >=3.8
